{
  "playerStart": {
    "x": 350,
    "y": 250,
    "angle": 0
  },
  "checkpoints": [],
  "style": {
    "platformTopColor": "rgba(82,82,82,1)",
    "platformSideColor": "rgba(82,82,82,1)",
    "wallTopColor": "rgba(82,82,82,1)",
    "wallSideColor": "rgba(82,82,82,1)",
    "endZoneTopColor": "rgba(250,250,250,1)",
    "endZoneSideColor": "rgba(255,255,255,1)",
    "backgroundColor": "rgb(201,201,201)",
    "playerColor": "rgba(235,235,235,1)",
    "directLight": "rgb(128,128,128)",
    "ambientLight": "rgb(207,226,231)",
    "platformHeight": 25,
    "wallHeight": 50,
    "lightDirection": 185,
    "lightPitch": 46
  },
  "platforms": [
    {
      "x": 360,
      "y": 8,
      "width": 25,
      "height": 25,
      "angle": 45,
      "angleRad": 0.7853981633974483,
      "endzone": 1,
      "wall": 0,
      "hypotenuse": 17.67766952966369,
      "corners": [
        [
          -17.67766952966369,
          1.7763568394002505e-15
        ],
        [
          1.7763568394002505e-15,
          17.67766952966369
        ],
        [
          17.67766952966369,
          -1.7763568394002505e-15
        ],
        [
          -1.7763568394002505e-15,
          -17.67766952966369
        ]
      ],
      "cornersSorted": [
        [
          -17.67766952966369,
          1.7763568394002505e-15
        ],
        [
          -1.7763568394002505e-15,
          -17.67766952966369
        ],
        [
          1.7763568394002505e-15,
          17.67766952966369
        ],
        [
          17.67766952966369,
          -1.7763568394002505e-15
        ]
      ],
      "leftMostCornerX": 342.3223304703363,
      "leftMostCornerY": 8.000000000000002,
      "rightMostCornerX": 377.6776695296637,
      "rightMostCornerY": 7.999999999999998,
      "topCornerX": 360,
      "topCornerY": -9.677669529663689,
      "botCornerX": 360,
      "botCornerY": 25.67766952966369,
      "occludes": []
    },
    {
      "x": 324,
      "y": 50,
      "width": 50,
      "height": 50,
      "angle": 45,
      "angleRad": 0.7853981633974483,
      "endzone": 1,
      "wall": 0,
      "hypotenuse": 35.35533905932738,
      "corners": [
        [
          -35.35533905932738,
          3.552713678800501e-15
        ],
        [
          3.552713678800501e-15,
          35.35533905932738
        ],
        [
          35.35533905932738,
          -3.552713678800501e-15
        ],
        [
          -3.552713678800501e-15,
          -35.35533905932738
        ]
      ],
      "cornersSorted": [
        [
          -35.35533905932738,
          3.552713678800501e-15
        ],
        [
          -3.552713678800501e-15,
          -35.35533905932738
        ],
        [
          3.552713678800501e-15,
          35.35533905932738
        ],
        [
          35.35533905932738,
          -3.552713678800501e-15
        ]
      ],
      "leftMostCornerX": 288.6446609406726,
      "leftMostCornerY": 50,
      "rightMostCornerX": 359.3553390593274,
      "rightMostCornerY": 50,
      "topCornerX": 324,
      "topCornerY": 14.644660940672622,
      "botCornerX": 324,
      "botCornerY": 85.35533905932738,
      "occludes": [
        0
      ]
    },
    {
      "x": 501,
      "y": 8,
      "width": 25,
      "height": 25,
      "angle": 45,
      "angleRad": 0.7853981633974483,
      "endzone": 1,
      "wall": 0,
      "hypotenuse": 17.67766952966369,
      "corners": [
        [
          -17.67766952966369,
          1.7763568394002505e-15
        ],
        [
          1.7763568394002505e-15,
          17.67766952966369
        ],
        [
          17.67766952966369,
          -1.7763568394002505e-15
        ],
        [
          -1.7763568394002505e-15,
          -17.67766952966369
        ]
      ],
      "cornersSorted": [
        [
          -17.67766952966369,
          1.7763568394002505e-15
        ],
        [
          -1.7763568394002505e-15,
          -17.67766952966369
        ],
        [
          1.7763568394002505e-15,
          17.67766952966369
        ],
        [
          17.67766952966369,
          -1.7763568394002505e-15
        ]
      ],
      "leftMostCornerX": 483.3223304703363,
      "leftMostCornerY": 8.000000000000002,
      "rightMostCornerX": 518.6776695296637,
      "rightMostCornerY": 7.999999999999998,
      "topCornerX": 501,
      "topCornerY": -9.677669529663689,
      "botCornerX": 501,
      "botCornerY": 25.67766952966369,
      "occludes": []
    },
    {
      "x": 430,
      "y": 50,
      "width": 100,
      "height": 100,
      "angle": 45,
      "angleRad": 0.7853981633974483,
      "endzone": 1,
      "wall": 0,
      "hypotenuse": 70.71067811865476,
      "corners": [
        [
          -70.71067811865476,
          7.105427357601002e-15
        ],
        [
          7.105427357601002e-15,
          70.71067811865476
        ],
        [
          70.71067811865476,
          -7.105427357601002e-15
        ],
        [
          -7.105427357601002e-15,
          -70.71067811865476
        ]
      ],
      "cornersSorted": [
        [
          -70.71067811865476,
          7.105427357601002e-15
        ],
        [
          -7.105427357601002e-15,
          -70.71067811865476
        ],
        [
          7.105427357601002e-15,
          70.71067811865476
        ],
        [
          70.71067811865476,
          -7.105427357601002e-15
        ]
      ],
      "leftMostCornerX": 359.28932188134524,
      "leftMostCornerY": 50.00000000000001,
      "rightMostCornerX": 500.71067811865476,
      "rightMostCornerY": 49.99999999999999,
      "topCornerX": 430,
      "topCornerY": -20.710678118654755,
      "botCornerX": 430,
      "botCornerY": 120.71067811865476,
      "occludes": [
        0,
        1,
        2
      ]
    },
    {
      "x": 350,
      "y": 250,
      "width": 60,
      "height": 60,
      "angle": 45,
      "angleRad": 0.7853981633974483,
      "endzone": 0,
      "wall": 0,
      "hypotenuse": 42.42640687119285,
      "corners": [
        [
          -42.42640687119285,
          3.552713678800501e-15
        ],
        [
          3.552713678800501e-15,
          42.42640687119285
        ],
        [
          42.42640687119285,
          -3.552713678800501e-15
        ],
        [
          -3.552713678800501e-15,
          -42.42640687119285
        ]
      ],
      "cornersSorted": [
        [
          -42.42640687119285,
          3.552713678800501e-15
        ],
        [
          -3.552713678800501e-15,
          -42.42640687119285
        ],
        [
          3.552713678800501e-15,
          42.42640687119285
        ],
        [
          42.42640687119285,
          -3.552713678800501e-15
        ]
      ],
      "leftMostCornerX": 307.57359312880715,
      "leftMostCornerY": 250,
      "rightMostCornerX": 392.42640687119285,
      "rightMostCornerY": 250,
      "topCornerX": 350,
      "topCornerY": 207.57359312880715,
      "botCornerX": 350,
      "botCornerY": 292.42640687119285,
      "occludes": []
    },
    {
      "x": 435,
      "y": 250,
      "width": 60,
      "height": 60,
      "angle": 45,
      "angleRad": 0.7853981633974483,
      "endzone": 0,
      "wall": 0,
      "hypotenuse": 42.42640687119285,
      "corners": [
        [
          -42.42640687119285,
          3.552713678800501e-15
        ],
        [
          3.552713678800501e-15,
          42.42640687119285
        ],
        [
          42.42640687119285,
          -3.552713678800501e-15
        ],
        [
          -3.552713678800501e-15,
          -42.42640687119285
        ]
      ],
      "cornersSorted": [
        [
          -42.42640687119285,
          3.552713678800501e-15
        ],
        [
          -3.552713678800501e-15,
          -42.42640687119285
        ],
        [
          3.552713678800501e-15,
          42.42640687119285
        ],
        [
          42.42640687119285,
          -3.552713678800501e-15
        ]
      ],
      "leftMostCornerX": 392.57359312880715,
      "leftMostCornerY": 250,
      "rightMostCornerX": 477.42640687119285,
      "rightMostCornerY": 250,
      "topCornerX": 435,
      "topCornerY": 207.57359312880715,
      "botCornerX": 435,
      "botCornerY": 292.42640687119285,
      "occludes": []
    },
    {
      "x": 350,
      "y": 335,
      "width": 60,
      "height": 60,
      "angle": 45,
      "angleRad": 0.7853981633974483,
      "endzone": 0,
      "wall": 0,
      "hypotenuse": 42.42640687119285,
      "corners": [
        [
          -42.42640687119285,
          3.552713678800501e-15
        ],
        [
          3.552713678800501e-15,
          42.42640687119285
        ],
        [
          42.42640687119285,
          -3.552713678800501e-15
        ],
        [
          -3.552713678800501e-15,
          -42.42640687119285
        ]
      ],
      "cornersSorted": [
        [
          -42.42640687119285,
          3.552713678800501e-15
        ],
        [
          -3.552713678800501e-15,
          -42.42640687119285
        ],
        [
          3.552713678800501e-15,
          42.42640687119285
        ],
        [
          42.42640687119285,
          -3.552713678800501e-15
        ]
      ],
      "leftMostCornerX": 307.57359312880715,
      "leftMostCornerY": 335,
      "rightMostCornerX": 392.42640687119285,
      "rightMostCornerY": 335,
      "topCornerX": 350,
      "topCornerY": 292.57359312880715,
      "botCornerX": 350,
      "botCornerY": 377.42640687119285,
      "occludes": [
        4
      ]
    },
    {
      "x": 435,
      "y": 335,
      "width": 60,
      "height": 60,
      "angle": 45,
      "angleRad": 0.7853981633974483,
      "endzone": 0,
      "wall": 0,
      "hypotenuse": 42.42640687119285,
      "corners": [
        [
          -42.42640687119285,
          3.552713678800501e-15
        ],
        [
          3.552713678800501e-15,
          42.42640687119285
        ],
        [
          42.42640687119285,
          -3.552713678800501e-15
        ],
        [
          -3.552713678800501e-15,
          -42.42640687119285
        ]
      ],
      "cornersSorted": [
        [
          -42.42640687119285,
          3.552713678800501e-15
        ],
        [
          -3.552713678800501e-15,
          -42.42640687119285
        ],
        [
          3.552713678800501e-15,
          42.42640687119285
        ],
        [
          42.42640687119285,
          -3.552713678800501e-15
        ]
      ],
      "leftMostCornerX": 392.57359312880715,
      "leftMostCornerY": 335,
      "rightMostCornerX": 477.42640687119285,
      "rightMostCornerY": 335,
      "topCornerX": 435,
      "topCornerY": 292.57359312880715,
      "botCornerX": 435,
      "botCornerY": 377.42640687119285,
      "occludes": [
        5
      ]
    },
    {
      "x": 520,
      "y": 250,
      "width": 60,
      "height": 60,
      "angle": 45,
      "angleRad": 0.7853981633974483,
      "endzone": 0,
      "wall": 0,
      "hypotenuse": 42.42640687119285,
      "corners": [
        [
          -42.42640687119285,
          3.552713678800501e-15
        ],
        [
          3.552713678800501e-15,
          42.42640687119285
        ],
        [
          42.42640687119285,
          -3.552713678800501e-15
        ],
        [
          -3.552713678800501e-15,
          -42.42640687119285
        ]
      ],
      "cornersSorted": [
        [
          -42.42640687119285,
          3.552713678800501e-15
        ],
        [
          -3.552713678800501e-15,
          -42.42640687119285
        ],
        [
          3.552713678800501e-15,
          42.42640687119285
        ],
        [
          42.42640687119285,
          -3.552713678800501e-15
        ]
      ],
      "leftMostCornerX": 477.57359312880715,
      "leftMostCornerY": 250,
      "rightMostCornerX": 562.4264068711929,
      "rightMostCornerY": 250,
      "topCornerX": 520,
      "topCornerY": 207.57359312880715,
      "botCornerX": 520,
      "botCornerY": 292.42640687119285,
      "occludes": []
    },
    {
      "x": 520,
      "y": 335,
      "width": 60,
      "height": 60,
      "angle": 45,
      "angleRad": 0.7853981633974483,
      "endzone": 0,
      "wall": 0,
      "hypotenuse": 42.42640687119285,
      "corners": [
        [
          -42.42640687119285,
          3.552713678800501e-15
        ],
        [
          3.552713678800501e-15,
          42.42640687119285
        ],
        [
          42.42640687119285,
          -3.552713678800501e-15
        ],
        [
          -3.552713678800501e-15,
          -42.42640687119285
        ]
      ],
      "cornersSorted": [
        [
          -42.42640687119285,
          3.552713678800501e-15
        ],
        [
          -3.552713678800501e-15,
          -42.42640687119285
        ],
        [
          3.552713678800501e-15,
          42.42640687119285
        ],
        [
          42.42640687119285,
          -3.552713678800501e-15
        ]
      ],
      "leftMostCornerX": 477.57359312880715,
      "leftMostCornerY": 335,
      "rightMostCornerX": 562.4264068711929,
      "rightMostCornerY": 335,
      "topCornerX": 520,
      "topCornerY": 292.57359312880715,
      "botCornerX": 520,
      "botCornerY": 377.42640687119285,
      "occludes": [
        8
      ]
    },
    {
      "x": 350,
      "y": 420,
      "width": 60,
      "height": 60,
      "angle": 45,
      "angleRad": 0.7853981633974483,
      "endzone": 0,
      "wall": 0,
      "hypotenuse": 42.42640687119285,
      "corners": [
        [
          -42.42640687119285,
          3.552713678800501e-15
        ],
        [
          3.552713678800501e-15,
          42.42640687119285
        ],
        [
          42.42640687119285,
          -3.552713678800501e-15
        ],
        [
          -3.552713678800501e-15,
          -42.42640687119285
        ]
      ],
      "cornersSorted": [
        [
          -42.42640687119285,
          3.552713678800501e-15
        ],
        [
          -3.552713678800501e-15,
          -42.42640687119285
        ],
        [
          3.552713678800501e-15,
          42.42640687119285
        ],
        [
          42.42640687119285,
          -3.552713678800501e-15
        ]
      ],
      "leftMostCornerX": 307.57359312880715,
      "leftMostCornerY": 420,
      "rightMostCornerX": 392.42640687119285,
      "rightMostCornerY": 420,
      "topCornerX": 350,
      "topCornerY": 377.57359312880715,
      "botCornerX": 350,
      "botCornerY": 462.42640687119285,
      "occludes": [
        6
      ]
    },
    {
      "x": 435,
      "y": 420,
      "width": 60,
      "height": 60,
      "angle": 45,
      "angleRad": 0.7853981633974483,
      "endzone": 0,
      "wall": 0,
      "hypotenuse": 42.42640687119285,
      "corners": [
        [
          -42.42640687119285,
          3.552713678800501e-15
        ],
        [
          3.552713678800501e-15,
          42.42640687119285
        ],
        [
          42.42640687119285,
          -3.552713678800501e-15
        ],
        [
          -3.552713678800501e-15,
          -42.42640687119285
        ]
      ],
      "cornersSorted": [
        [
          -42.42640687119285,
          3.552713678800501e-15
        ],
        [
          -3.552713678800501e-15,
          -42.42640687119285
        ],
        [
          3.552713678800501e-15,
          42.42640687119285
        ],
        [
          42.42640687119285,
          -3.552713678800501e-15
        ]
      ],
      "leftMostCornerX": 392.57359312880715,
      "leftMostCornerY": 420,
      "rightMostCornerX": 477.42640687119285,
      "rightMostCornerY": 420,
      "topCornerX": 435,
      "topCornerY": 377.57359312880715,
      "botCornerX": 435,
      "botCornerY": 462.42640687119285,
      "occludes": [
        7
      ]
    },
    {
      "x": 520,
      "y": 420,
      "width": 60,
      "height": 60,
      "angle": 45,
      "angleRad": 0.7853981633974483,
      "endzone": 0,
      "wall": 0,
      "hypotenuse": 42.42640687119285,
      "corners": [
        [
          -42.42640687119285,
          3.552713678800501e-15
        ],
        [
          3.552713678800501e-15,
          42.42640687119285
        ],
        [
          42.42640687119285,
          -3.552713678800501e-15
        ],
        [
          -3.552713678800501e-15,
          -42.42640687119285
        ]
      ],
      "cornersSorted": [
        [
          -42.42640687119285,
          3.552713678800501e-15
        ],
        [
          -3.552713678800501e-15,
          -42.42640687119285
        ],
        [
          3.552713678800501e-15,
          42.42640687119285
        ],
        [
          42.42640687119285,
          -3.552713678800501e-15
        ]
      ],
      "leftMostCornerX": 477.57359312880715,
      "leftMostCornerY": 420,
      "rightMostCornerX": 562.4264068711929,
      "rightMostCornerY": 420,
      "topCornerX": 520,
      "topCornerY": 377.57359312880715,
      "botCornerX": 520,
      "botCornerY": 462.42640687119285,
      "occludes": [
        9
      ]
    },
    {
      "x": 710,
      "y": 250,
      "width": 120,
      "height": 120,
      "angle": 45,
      "angleRad": 0.7853981633974483,
      "endzone": 0,
      "wall": 0,
      "hypotenuse": 84.8528137423857,
      "corners": [
        [
          -84.8528137423857,
          7.105427357601002e-15
        ],
        [
          7.105427357601002e-15,
          84.8528137423857
        ],
        [
          84.8528137423857,
          -7.105427357601002e-15
        ],
        [
          -7.105427357601002e-15,
          -84.8528137423857
        ]
      ],
      "cornersSorted": [
        [
          -84.8528137423857,
          7.105427357601002e-15
        ],
        [
          -7.105427357601002e-15,
          -84.8528137423857
        ],
        [
          7.105427357601002e-15,
          84.8528137423857
        ],
        [
          84.8528137423857,
          -7.105427357601002e-15
        ]
      ],
      "leftMostCornerX": 625.1471862576143,
      "leftMostCornerY": 250,
      "rightMostCornerX": 794.8528137423857,
      "rightMostCornerY": 250,
      "topCornerX": 710,
      "topCornerY": 165.1471862576143,
      "botCornerX": 710,
      "botCornerY": 334.8528137423857,
      "occludes": []
    },
    {
      "x": 970,
      "y": 250,
      "width": 120,
      "height": 120,
      "angle": 45,
      "angleRad": 0.7853981633974483,
      "endzone": 0,
      "wall": 0,
      "hypotenuse": 84.8528137423857,
      "corners": [
        [
          -84.8528137423857,
          7.105427357601002e-15
        ],
        [
          7.105427357601002e-15,
          84.8528137423857
        ],
        [
          84.8528137423857,
          -7.105427357601002e-15
        ],
        [
          -7.105427357601002e-15,
          -84.8528137423857
        ]
      ],
      "cornersSorted": [
        [
          -84.8528137423857,
          7.105427357601002e-15
        ],
        [
          -7.105427357601002e-15,
          -84.8528137423857
        ],
        [
          7.105427357601002e-15,
          84.8528137423857
        ],
        [
          84.8528137423857,
          -7.105427357601002e-15
        ]
      ],
      "leftMostCornerX": 885.1471862576143,
      "leftMostCornerY": 250,
      "rightMostCornerX": 1054.8528137423857,
      "rightMostCornerY": 250,
      "topCornerX": 970,
      "topCornerY": 165.1471862576143,
      "botCornerX": 970,
      "botCornerY": 334.8528137423857,
      "occludes": []
    },
    {
      "x": 710,
      "y": 380,
      "width": 60,
      "height": 60,
      "angle": 45,
      "angleRad": 0.7853981633974483,
      "endzone": 0,
      "wall": 0,
      "hypotenuse": 42.42640687119285,
      "corners": [
        [
          -42.42640687119285,
          3.552713678800501e-15
        ],
        [
          3.552713678800501e-15,
          42.42640687119285
        ],
        [
          42.42640687119285,
          -3.552713678800501e-15
        ],
        [
          -3.552713678800501e-15,
          -42.42640687119285
        ]
      ],
      "cornersSorted": [
        [
          -42.42640687119285,
          3.552713678800501e-15
        ],
        [
          -3.552713678800501e-15,
          -42.42640687119285
        ],
        [
          3.552713678800501e-15,
          42.42640687119285
        ],
        [
          42.42640687119285,
          -3.552713678800501e-15
        ]
      ],
      "leftMostCornerX": 667.5735931288071,
      "leftMostCornerY": 380,
      "rightMostCornerX": 752.4264068711929,
      "rightMostCornerY": 380,
      "topCornerX": 710,
      "topCornerY": 337.57359312880715,
      "botCornerX": 710,
      "botCornerY": 422.42640687119285,
      "occludes": [
        13
      ]
    },
    {
      "x": 840,
      "y": 250,
      "width": 60,
      "height": 60,
      "angle": 45,
      "angleRad": 0.7853981633974483,
      "endzone": 0,
      "wall": 0,
      "hypotenuse": 42.42640687119285,
      "corners": [
        [
          -42.42640687119285,
          3.552713678800501e-15
        ],
        [
          3.552713678800501e-15,
          42.42640687119285
        ],
        [
          42.42640687119285,
          -3.552713678800501e-15
        ],
        [
          -3.552713678800501e-15,
          -42.42640687119285
        ]
      ],
      "cornersSorted": [
        [
          -42.42640687119285,
          3.552713678800501e-15
        ],
        [
          -3.552713678800501e-15,
          -42.42640687119285
        ],
        [
          3.552713678800501e-15,
          42.42640687119285
        ],
        [
          42.42640687119285,
          -3.552713678800501e-15
        ]
      ],
      "leftMostCornerX": 797.5735931288071,
      "leftMostCornerY": 250,
      "rightMostCornerX": 882.4264068711929,
      "rightMostCornerY": 250,
      "topCornerX": 840,
      "topCornerY": 207.57359312880715,
      "botCornerX": 840,
      "botCornerY": 292.42640687119285,
      "occludes": []
    },
    {
      "x": 840,
      "y": 380,
      "width": 120,
      "height": 120,
      "angle": 45,
      "angleRad": 0.7853981633974483,
      "endzone": 0,
      "wall": 0,
      "hypotenuse": 84.8528137423857,
      "corners": [
        [
          -84.8528137423857,
          7.105427357601002e-15
        ],
        [
          7.105427357601002e-15,
          84.8528137423857
        ],
        [
          84.8528137423857,
          -7.105427357601002e-15
        ],
        [
          -7.105427357601002e-15,
          -84.8528137423857
        ]
      ],
      "cornersSorted": [
        [
          -84.8528137423857,
          7.105427357601002e-15
        ],
        [
          -7.105427357601002e-15,
          -84.8528137423857
        ],
        [
          7.105427357601002e-15,
          84.8528137423857
        ],
        [
          84.8528137423857,
          -7.105427357601002e-15
        ]
      ],
      "leftMostCornerX": 755.1471862576143,
      "leftMostCornerY": 380,
      "rightMostCornerX": 924.8528137423857,
      "rightMostCornerY": 380,
      "topCornerX": 840,
      "topCornerY": 295.1471862576143,
      "botCornerX": 840,
      "botCornerY": 464.8528137423857,
      "occludes": [
        13,
        14,
        16
      ]
    },
    {
      "x": 710,
      "y": 510,
      "width": 120,
      "height": 120,
      "angle": 45,
      "angleRad": 0.7853981633974483,
      "endzone": 0,
      "wall": 0,
      "hypotenuse": 84.8528137423857,
      "corners": [
        [
          -84.8528137423857,
          7.105427357601002e-15
        ],
        [
          7.105427357601002e-15,
          84.8528137423857
        ],
        [
          84.8528137423857,
          -7.105427357601002e-15
        ],
        [
          -7.105427357601002e-15,
          -84.8528137423857
        ]
      ],
      "cornersSorted": [
        [
          -84.8528137423857,
          7.105427357601002e-15
        ],
        [
          -7.105427357601002e-15,
          -84.8528137423857
        ],
        [
          7.105427357601002e-15,
          84.8528137423857
        ],
        [
          84.8528137423857,
          -7.105427357601002e-15
        ]
      ],
      "leftMostCornerX": 625.1471862576143,
      "leftMostCornerY": 510,
      "rightMostCornerX": 794.8528137423857,
      "rightMostCornerY": 510,
      "topCornerX": 710,
      "topCornerY": 425.1471862576143,
      "botCornerX": 710,
      "botCornerY": 594.8528137423857,
      "occludes": [
        15,
        17
      ]
    },
    {
      "x": 970,
      "y": 380,
      "width": 60,
      "height": 60,
      "angle": 45,
      "angleRad": 0.7853981633974483,
      "endzone": 0,
      "wall": 0,
      "hypotenuse": 42.42640687119285,
      "corners": [
        [
          -42.42640687119285,
          3.552713678800501e-15
        ],
        [
          3.552713678800501e-15,
          42.42640687119285
        ],
        [
          42.42640687119285,
          -3.552713678800501e-15
        ],
        [
          -3.552713678800501e-15,
          -42.42640687119285
        ]
      ],
      "cornersSorted": [
        [
          -42.42640687119285,
          3.552713678800501e-15
        ],
        [
          -3.552713678800501e-15,
          -42.42640687119285
        ],
        [
          3.552713678800501e-15,
          42.42640687119285
        ],
        [
          42.42640687119285,
          -3.552713678800501e-15
        ]
      ],
      "leftMostCornerX": 927.5735931288071,
      "leftMostCornerY": 380,
      "rightMostCornerX": 1012.4264068711929,
      "rightMostCornerY": 380,
      "topCornerX": 970,
      "topCornerY": 337.57359312880715,
      "botCornerX": 970,
      "botCornerY": 422.42640687119285,
      "occludes": [
        14
      ]
    },
    {
      "x": 840,
      "y": 510,
      "width": 60,
      "height": 60,
      "angle": 45,
      "angleRad": 0.7853981633974483,
      "endzone": 0,
      "wall": 0,
      "hypotenuse": 42.42640687119285,
      "corners": [
        [
          -42.42640687119285,
          3.552713678800501e-15
        ],
        [
          3.552713678800501e-15,
          42.42640687119285
        ],
        [
          42.42640687119285,
          -3.552713678800501e-15
        ],
        [
          -3.552713678800501e-15,
          -42.42640687119285
        ]
      ],
      "cornersSorted": [
        [
          -42.42640687119285,
          3.552713678800501e-15
        ],
        [
          -3.552713678800501e-15,
          -42.42640687119285
        ],
        [
          3.552713678800501e-15,
          42.42640687119285
        ],
        [
          42.42640687119285,
          -3.552713678800501e-15
        ]
      ],
      "leftMostCornerX": 797.5735931288071,
      "leftMostCornerY": 510,
      "rightMostCornerX": 882.4264068711929,
      "rightMostCornerY": 510,
      "topCornerX": 840,
      "topCornerY": 467.57359312880715,
      "botCornerX": 840,
      "botCornerY": 552.4264068711929,
      "occludes": [
        17
      ]
    },
    {
      "x": 970,
      "y": 510,
      "width": 120,
      "height": 120,
      "angle": 45,
      "angleRad": 0.7853981633974483,
      "endzone": 0,
      "wall": 0,
      "hypotenuse": 84.8528137423857,
      "corners": [
        [
          -84.8528137423857,
          7.105427357601002e-15
        ],
        [
          7.105427357601002e-15,
          84.8528137423857
        ],
        [
          84.8528137423857,
          -7.105427357601002e-15
        ],
        [
          -7.105427357601002e-15,
          -84.8528137423857
        ]
      ],
      "cornersSorted": [
        [
          -84.8528137423857,
          7.105427357601002e-15
        ],
        [
          -7.105427357601002e-15,
          -84.8528137423857
        ],
        [
          7.105427357601002e-15,
          84.8528137423857
        ],
        [
          84.8528137423857,
          -7.105427357601002e-15
        ]
      ],
      "leftMostCornerX": 885.1471862576143,
      "leftMostCornerY": 510,
      "rightMostCornerX": 1054.8528137423857,
      "rightMostCornerY": 510,
      "topCornerX": 970,
      "topCornerY": 425.1471862576143,
      "botCornerX": 970,
      "botCornerY": 594.8528137423857,
      "occludes": [
        17,
        19
      ]
    },
    {
      "x": 536,
      "y": 50,
      "width": 50,
      "height": 50,
      "angle": 45,
      "angleRad": 0.7853981633974483,
      "endzone": 1,
      "wall": 0,
      "hypotenuse": 35.35533905932738,
      "corners": [
        [
          -35.35533905932738,
          3.552713678800501e-15
        ],
        [
          3.552713678800501e-15,
          35.35533905932738
        ],
        [
          35.35533905932738,
          -3.552713678800501e-15
        ],
        [
          -3.552713678800501e-15,
          -35.35533905932738
        ]
      ],
      "cornersSorted": [
        [
          -35.35533905932738,
          3.552713678800501e-15
        ],
        [
          -3.552713678800501e-15,
          -35.35533905932738
        ],
        [
          3.552713678800501e-15,
          35.35533905932738
        ],
        [
          35.35533905932738,
          -3.552713678800501e-15
        ]
      ],
      "leftMostCornerX": 500.6446609406726,
      "leftMostCornerY": 50,
      "rightMostCornerX": 571.3553390593274,
      "rightMostCornerY": 50,
      "topCornerX": 536,
      "topCornerY": 14.644660940672622,
      "botCornerX": 536,
      "botCornerY": 85.35533905932738,
      "occludes": [
        2,
        3
      ]
    },
    {
      "x": 501,
      "y": 110,
      "width": 50,
      "height": 50,
      "angle": 45,
      "angleRad": 0.7853981633974483,
      "endzone": 1,
      "wall": 0,
      "hypotenuse": 35.35533905932738,
      "corners": [
        [
          -35.35533905932738,
          3.552713678800501e-15
        ],
        [
          3.552713678800501e-15,
          35.35533905932738
        ],
        [
          35.35533905932738,
          -3.552713678800501e-15
        ],
        [
          -3.552713678800501e-15,
          -35.35533905932738
        ]
      ],
      "cornersSorted": [
        [
          -35.35533905932738,
          3.552713678800501e-15
        ],
        [
          -3.552713678800501e-15,
          -35.35533905932738
        ],
        [
          3.552713678800501e-15,
          35.35533905932738
        ],
        [
          35.35533905932738,
          -3.552713678800501e-15
        ]
      ],
      "leftMostCornerX": 465.6446609406726,
      "leftMostCornerY": 110,
      "rightMostCornerX": 536.3553390593274,
      "rightMostCornerY": 110,
      "topCornerX": 501,
      "topCornerY": 74.64466094067262,
      "botCornerX": 501,
      "botCornerY": 145.35533905932738,
      "occludes": [
        3,
        22
      ]
    },
    {
      "x": 359,
      "y": 110,
      "width": 50,
      "height": 50,
      "angle": 45,
      "angleRad": 0.7853981633974483,
      "endzone": 1,
      "wall": 0,
      "hypotenuse": 35.35533905932738,
      "corners": [
        [
          -35.35533905932738,
          3.552713678800501e-15
        ],
        [
          3.552713678800501e-15,
          35.35533905932738
        ],
        [
          35.35533905932738,
          -3.552713678800501e-15
        ],
        [
          -3.552713678800501e-15,
          -35.35533905932738
        ]
      ],
      "cornersSorted": [
        [
          -35.35533905932738,
          3.552713678800501e-15
        ],
        [
          -3.552713678800501e-15,
          -35.35533905932738
        ],
        [
          3.552713678800501e-15,
          35.35533905932738
        ],
        [
          35.35533905932738,
          -3.552713678800501e-15
        ]
      ],
      "leftMostCornerX": 323.6446609406726,
      "leftMostCornerY": 110,
      "rightMostCornerX": 394.3553390593274,
      "rightMostCornerY": 110,
      "topCornerX": 359,
      "topCornerY": 74.64466094067262,
      "botCornerX": 359,
      "botCornerY": 145.35533905932738,
      "occludes": [
        1,
        3
      ]
    },
    {
      "x": 430,
      "y": 139,
      "width": 25,
      "height": 25,
      "angle": 45,
      "angleRad": 0.7853981633974483,
      "endzone": 1,
      "wall": 0,
      "hypotenuse": 17.67766952966369,
      "corners": [
        [
          -17.67766952966369,
          1.7763568394002505e-15
        ],
        [
          1.7763568394002505e-15,
          17.67766952966369
        ],
        [
          17.67766952966369,
          -1.7763568394002505e-15
        ],
        [
          -1.7763568394002505e-15,
          -17.67766952966369
        ]
      ],
      "cornersSorted": [
        [
          -17.67766952966369,
          1.7763568394002505e-15
        ],
        [
          -1.7763568394002505e-15,
          -17.67766952966369
        ],
        [
          1.7763568394002505e-15,
          17.67766952966369
        ],
        [
          17.67766952966369,
          -1.7763568394002505e-15
        ]
      ],
      "leftMostCornerX": 412.3223304703363,
      "leftMostCornerY": 139,
      "rightMostCornerX": 447.6776695296637,
      "rightMostCornerY": 139,
      "topCornerX": 430,
      "topCornerY": 121.32233047033631,
      "botCornerX": 430,
      "botCornerY": 156.6776695296637,
      "occludes": [
        3
      ]
    },
    {
      "x": 530,
      "y": 535,
      "width": 5,
      "height": 5,
      "angle": 45,
      "angleRad": 0.7853981633974483,
      "endzone": 0,
      "wall": 0,
      "hypotenuse": 3.5355339059327378,
      "corners": [
        [
          -3.5355339059327378,
          2.220446049250313e-16
        ],
        [
          2.220446049250313e-16,
          3.5355339059327378
        ],
        [
          3.5355339059327378,
          -2.220446049250313e-16
        ],
        [
          -2.220446049250313e-16,
          -3.5355339059327378
        ]
      ],
      "cornersSorted": [
        [
          -3.5355339059327378,
          2.220446049250313e-16
        ],
        [
          -2.220446049250313e-16,
          -3.5355339059327378
        ],
        [
          2.220446049250313e-16,
          3.5355339059327378
        ],
        [
          3.5355339059327378,
          -2.220446049250313e-16
        ]
      ],
      "leftMostCornerX": 526.4644660940672,
      "leftMostCornerY": 535,
      "rightMostCornerX": 533.5355339059328,
      "rightMostCornerY": 535,
      "topCornerX": 530,
      "topCornerY": 531.4644660940672,
      "botCornerX": 530,
      "botCornerY": 538.5355339059328,
      "occludes": []
    },
    {
      "x": 537,
      "y": 535,
      "width": 5,
      "height": 5,
      "angle": 45,
      "angleRad": 0.7853981633974483,
      "endzone": 0,
      "wall": 0,
      "hypotenuse": 3.5355339059327378,
      "corners": [
        [
          -3.5355339059327378,
          2.220446049250313e-16
        ],
        [
          2.220446049250313e-16,
          3.5355339059327378
        ],
        [
          3.5355339059327378,
          -2.220446049250313e-16
        ],
        [
          -2.220446049250313e-16,
          -3.5355339059327378
        ]
      ],
      "cornersSorted": [
        [
          -3.5355339059327378,
          2.220446049250313e-16
        ],
        [
          -2.220446049250313e-16,
          -3.5355339059327378
        ],
        [
          2.220446049250313e-16,
          3.5355339059327378
        ],
        [
          3.5355339059327378,
          -2.220446049250313e-16
        ]
      ],
      "leftMostCornerX": 533.4644660940672,
      "leftMostCornerY": 535,
      "rightMostCornerX": 540.5355339059328,
      "rightMostCornerY": 535,
      "topCornerX": 537,
      "topCornerY": 531.4644660940672,
      "botCornerX": 537,
      "botCornerY": 538.5355339059328,
      "occludes": []
    },
    {
      "x": 544,
      "y": 535,
      "width": 5,
      "height": 5,
      "angle": 45,
      "angleRad": 0.7853981633974483,
      "endzone": 0,
      "wall": 0,
      "hypotenuse": 3.5355339059327378,
      "corners": [
        [
          -3.5355339059327378,
          2.220446049250313e-16
        ],
        [
          2.220446049250313e-16,
          3.5355339059327378
        ],
        [
          3.5355339059327378,
          -2.220446049250313e-16
        ],
        [
          -2.220446049250313e-16,
          -3.5355339059327378
        ]
      ],
      "cornersSorted": [
        [
          -3.5355339059327378,
          2.220446049250313e-16
        ],
        [
          -2.220446049250313e-16,
          -3.5355339059327378
        ],
        [
          2.220446049250313e-16,
          3.5355339059327378
        ],
        [
          3.5355339059327378,
          -2.220446049250313e-16
        ]
      ],
      "leftMostCornerX": 540.4644660940672,
      "leftMostCornerY": 535,
      "rightMostCornerX": 547.5355339059328,
      "rightMostCornerY": 535,
      "topCornerX": 544,
      "topCornerY": 531.4644660940672,
      "botCornerX": 544,
      "botCornerY": 538.5355339059328,
      "occludes": []
    },
    {
      "x": 551,
      "y": 535,
      "width": 5,
      "height": 5,
      "angle": 45,
      "angleRad": 0.7853981633974483,
      "endzone": 0,
      "wall": 0,
      "hypotenuse": 3.5355339059327378,
      "corners": [
        [
          -3.5355339059327378,
          2.220446049250313e-16
        ],
        [
          2.220446049250313e-16,
          3.5355339059327378
        ],
        [
          3.5355339059327378,
          -2.220446049250313e-16
        ],
        [
          -2.220446049250313e-16,
          -3.5355339059327378
        ]
      ],
      "cornersSorted": [
        [
          -3.5355339059327378,
          2.220446049250313e-16
        ],
        [
          -2.220446049250313e-16,
          -3.5355339059327378
        ],
        [
          2.220446049250313e-16,
          3.5355339059327378
        ],
        [
          3.5355339059327378,
          -2.220446049250313e-16
        ]
      ],
      "leftMostCornerX": 547.4644660940672,
      "leftMostCornerY": 535,
      "rightMostCornerX": 554.5355339059328,
      "rightMostCornerY": 535,
      "topCornerX": 551,
      "topCornerY": 531.4644660940672,
      "botCornerX": 551,
      "botCornerY": 538.5355339059328,
      "occludes": []
    },
    {
      "x": 558,
      "y": 535,
      "width": 5,
      "height": 5,
      "angle": 45,
      "angleRad": 0.7853981633974483,
      "endzone": 0,
      "wall": 0,
      "hypotenuse": 3.5355339059327378,
      "corners": [
        [
          -3.5355339059327378,
          2.220446049250313e-16
        ],
        [
          2.220446049250313e-16,
          3.5355339059327378
        ],
        [
          3.5355339059327378,
          -2.220446049250313e-16
        ],
        [
          -2.220446049250313e-16,
          -3.5355339059327378
        ]
      ],
      "cornersSorted": [
        [
          -3.5355339059327378,
          2.220446049250313e-16
        ],
        [
          -2.220446049250313e-16,
          -3.5355339059327378
        ],
        [
          2.220446049250313e-16,
          3.5355339059327378
        ],
        [
          3.5355339059327378,
          -2.220446049250313e-16
        ]
      ],
      "leftMostCornerX": 554.4644660940672,
      "leftMostCornerY": 535,
      "rightMostCornerX": 561.5355339059328,
      "rightMostCornerY": 535,
      "topCornerX": 558,
      "topCornerY": 531.4644660940672,
      "botCornerX": 558,
      "botCornerY": 538.5355339059328,
      "occludes": []
    },
    {
      "x": 565,
      "y": 535,
      "width": 5,
      "height": 5,
      "angle": 45,
      "angleRad": 0.7853981633974483,
      "endzone": 0,
      "wall": 0,
      "hypotenuse": 3.5355339059327378,
      "corners": [
        [
          -3.5355339059327378,
          2.220446049250313e-16
        ],
        [
          2.220446049250313e-16,
          3.5355339059327378
        ],
        [
          3.5355339059327378,
          -2.220446049250313e-16
        ],
        [
          -2.220446049250313e-16,
          -3.5355339059327378
        ]
      ],
      "cornersSorted": [
        [
          -3.5355339059327378,
          2.220446049250313e-16
        ],
        [
          -2.220446049250313e-16,
          -3.5355339059327378
        ],
        [
          2.220446049250313e-16,
          3.5355339059327378
        ],
        [
          3.5355339059327378,
          -2.220446049250313e-16
        ]
      ],
      "leftMostCornerX": 561.4644660940672,
      "leftMostCornerY": 535,
      "rightMostCornerX": 568.5355339059328,
      "rightMostCornerY": 535,
      "topCornerX": 565,
      "topCornerY": 531.4644660940672,
      "botCornerX": 565,
      "botCornerY": 538.5355339059328,
      "occludes": []
    },
    {
      "x": 463,
      "y": 542,
      "width": 5,
      "height": 5,
      "angle": 45,
      "angleRad": 0.7853981633974483,
      "endzone": 0,
      "wall": 0,
      "hypotenuse": 3.5355339059327378,
      "corners": [
        [
          -3.5355339059327378,
          2.220446049250313e-16
        ],
        [
          2.220446049250313e-16,
          3.5355339059327378
        ],
        [
          3.5355339059327378,
          -2.220446049250313e-16
        ],
        [
          -2.220446049250313e-16,
          -3.5355339059327378
        ]
      ],
      "cornersSorted": [
        [
          -3.5355339059327378,
          2.220446049250313e-16
        ],
        [
          -2.220446049250313e-16,
          -3.5355339059327378
        ],
        [
          2.220446049250313e-16,
          3.5355339059327378
        ],
        [
          3.5355339059327378,
          -2.220446049250313e-16
        ]
      ],
      "leftMostCornerX": 459.46446609406723,
      "leftMostCornerY": 542,
      "rightMostCornerX": 466.53553390593277,
      "rightMostCornerY": 542,
      "topCornerX": 463,
      "topCornerY": 538.4644660940672,
      "botCornerX": 463,
      "botCornerY": 545.5355339059328,
      "occludes": []
    },
    {
      "x": 470,
      "y": 542,
      "width": 5,
      "height": 5,
      "angle": 45,
      "angleRad": 0.7853981633974483,
      "endzone": 0,
      "wall": 0,
      "hypotenuse": 3.5355339059327378,
      "corners": [
        [
          -3.5355339059327378,
          2.220446049250313e-16
        ],
        [
          2.220446049250313e-16,
          3.5355339059327378
        ],
        [
          3.5355339059327378,
          -2.220446049250313e-16
        ],
        [
          -2.220446049250313e-16,
          -3.5355339059327378
        ]
      ],
      "cornersSorted": [
        [
          -3.5355339059327378,
          2.220446049250313e-16
        ],
        [
          -2.220446049250313e-16,
          -3.5355339059327378
        ],
        [
          2.220446049250313e-16,
          3.5355339059327378
        ],
        [
          3.5355339059327378,
          -2.220446049250313e-16
        ]
      ],
      "leftMostCornerX": 466.46446609406723,
      "leftMostCornerY": 542,
      "rightMostCornerX": 473.53553390593277,
      "rightMostCornerY": 542,
      "topCornerX": 470,
      "topCornerY": 538.4644660940672,
      "botCornerX": 470,
      "botCornerY": 545.5355339059328,
      "occludes": []
    },
    {
      "x": 470,
      "y": 549,
      "width": 5,
      "height": 5,
      "angle": 45,
      "angleRad": 0.7853981633974483,
      "endzone": 0,
      "wall": 0,
      "hypotenuse": 3.5355339059327378,
      "corners": [
        [
          -3.5355339059327378,
          2.220446049250313e-16
        ],
        [
          2.220446049250313e-16,
          3.5355339059327378
        ],
        [
          3.5355339059327378,
          -2.220446049250313e-16
        ],
        [
          -2.220446049250313e-16,
          -3.5355339059327378
        ]
      ],
      "cornersSorted": [
        [
          -3.5355339059327378,
          2.220446049250313e-16
        ],
        [
          -2.220446049250313e-16,
          -3.5355339059327378
        ],
        [
          2.220446049250313e-16,
          3.5355339059327378
        ],
        [
          3.5355339059327378,
          -2.220446049250313e-16
        ]
      ],
      "leftMostCornerX": 466.46446609406723,
      "leftMostCornerY": 549,
      "rightMostCornerX": 473.53553390593277,
      "rightMostCornerY": 549,
      "topCornerX": 470,
      "topCornerY": 545.4644660940672,
      "botCornerX": 470,
      "botCornerY": 552.5355339059328,
      "occludes": [
        32,
        33
      ]
    },
    {
      "x": 463,
      "y": 549,
      "width": 5,
      "height": 5,
      "angle": 45,
      "angleRad": 0.7853981633974483,
      "endzone": 0,
      "wall": 0,
      "hypotenuse": 3.5355339059327378,
      "corners": [
        [
          -3.5355339059327378,
          2.220446049250313e-16
        ],
        [
          2.220446049250313e-16,
          3.5355339059327378
        ],
        [
          3.5355339059327378,
          -2.220446049250313e-16
        ],
        [
          -2.220446049250313e-16,
          -3.5355339059327378
        ]
      ],
      "cornersSorted": [
        [
          -3.5355339059327378,
          2.220446049250313e-16
        ],
        [
          -2.220446049250313e-16,
          -3.5355339059327378
        ],
        [
          2.220446049250313e-16,
          3.5355339059327378
        ],
        [
          3.5355339059327378,
          -2.220446049250313e-16
        ]
      ],
      "leftMostCornerX": 459.46446609406723,
      "leftMostCornerY": 549,
      "rightMostCornerX": 466.53553390593277,
      "rightMostCornerY": 549,
      "topCornerX": 463,
      "topCornerY": 545.4644660940672,
      "botCornerX": 463,
      "botCornerY": 552.5355339059328,
      "occludes": [
        32,
        33
      ]
    },
    {
      "x": 555,
      "y": 600,
      "width": 5,
      "height": 5,
      "angle": 45,
      "angleRad": 0.7853981633974483,
      "endzone": 0,
      "wall": 0,
      "hypotenuse": 3.5355339059327378,
      "corners": [
        [
          -3.5355339059327378,
          2.220446049250313e-16
        ],
        [
          2.220446049250313e-16,
          3.5355339059327378
        ],
        [
          3.5355339059327378,
          -2.220446049250313e-16
        ],
        [
          -2.220446049250313e-16,
          -3.5355339059327378
        ]
      ],
      "cornersSorted": [
        [
          -3.5355339059327378,
          2.220446049250313e-16
        ],
        [
          -2.220446049250313e-16,
          -3.5355339059327378
        ],
        [
          2.220446049250313e-16,
          3.5355339059327378
        ],
        [
          3.5355339059327378,
          -2.220446049250313e-16
        ]
      ],
      "leftMostCornerX": 551.4644660940672,
      "leftMostCornerY": 600,
      "rightMostCornerX": 558.5355339059328,
      "rightMostCornerY": 600,
      "topCornerX": 555,
      "topCornerY": 596.4644660940672,
      "botCornerX": 555,
      "botCornerY": 603.5355339059328,
      "occludes": []
    },
    {
      "x": 540,
      "y": 600,
      "width": 5,
      "height": 5,
      "angle": 45,
      "angleRad": 0.7853981633974483,
      "endzone": 0,
      "wall": 0,
      "hypotenuse": 3.5355339059327378,
      "corners": [
        [
          -3.5355339059327378,
          2.220446049250313e-16
        ],
        [
          2.220446049250313e-16,
          3.5355339059327378
        ],
        [
          3.5355339059327378,
          -2.220446049250313e-16
        ],
        [
          -2.220446049250313e-16,
          -3.5355339059327378
        ]
      ],
      "cornersSorted": [
        [
          -3.5355339059327378,
          2.220446049250313e-16
        ],
        [
          -2.220446049250313e-16,
          -3.5355339059327378
        ],
        [
          2.220446049250313e-16,
          3.5355339059327378
        ],
        [
          3.5355339059327378,
          -2.220446049250313e-16
        ]
      ],
      "leftMostCornerX": 536.4644660940672,
      "leftMostCornerY": 600,
      "rightMostCornerX": 543.5355339059328,
      "rightMostCornerY": 600,
      "topCornerX": 540,
      "topCornerY": 596.4644660940672,
      "botCornerX": 540,
      "botCornerY": 603.5355339059328,
      "occludes": []
    },
    {
      "x": 570,
      "y": 600,
      "width": 5,
      "height": 5,
      "angle": 45,
      "angleRad": 0.7853981633974483,
      "endzone": 0,
      "wall": 0,
      "hypotenuse": 3.5355339059327378,
      "corners": [
        [
          -3.5355339059327378,
          2.220446049250313e-16
        ],
        [
          2.220446049250313e-16,
          3.5355339059327378
        ],
        [
          3.5355339059327378,
          -2.220446049250313e-16
        ],
        [
          -2.220446049250313e-16,
          -3.5355339059327378
        ]
      ],
      "cornersSorted": [
        [
          -3.5355339059327378,
          2.220446049250313e-16
        ],
        [
          -2.220446049250313e-16,
          -3.5355339059327378
        ],
        [
          2.220446049250313e-16,
          3.5355339059327378
        ],
        [
          3.5355339059327378,
          -2.220446049250313e-16
        ]
      ],
      "leftMostCornerX": 566.4644660940672,
      "leftMostCornerY": 600,
      "rightMostCornerX": 573.5355339059328,
      "rightMostCornerY": 600,
      "topCornerX": 570,
      "topCornerY": 596.4644660940672,
      "botCornerX": 570,
      "botCornerY": 603.5355339059328,
      "occludes": []
    },
    {
      "x": 585,
      "y": 600,
      "width": 5,
      "height": 5,
      "angle": 45,
      "angleRad": 0.7853981633974483,
      "endzone": 0,
      "wall": 0,
      "hypotenuse": 3.5355339059327378,
      "corners": [
        [
          -3.5355339059327378,
          2.220446049250313e-16
        ],
        [
          2.220446049250313e-16,
          3.5355339059327378
        ],
        [
          3.5355339059327378,
          -2.220446049250313e-16
        ],
        [
          -2.220446049250313e-16,
          -3.5355339059327378
        ]
      ],
      "cornersSorted": [
        [
          -3.5355339059327378,
          2.220446049250313e-16
        ],
        [
          -2.220446049250313e-16,
          -3.5355339059327378
        ],
        [
          2.220446049250313e-16,
          3.5355339059327378
        ],
        [
          3.5355339059327378,
          -2.220446049250313e-16
        ]
      ],
      "leftMostCornerX": 581.4644660940672,
      "leftMostCornerY": 600,
      "rightMostCornerX": 588.5355339059328,
      "rightMostCornerY": 600,
      "topCornerX": 585,
      "topCornerY": 596.4644660940672,
      "botCornerX": 585,
      "botCornerY": 603.5355339059328,
      "occludes": []
    },
    {
      "x": 540,
      "y": 615,
      "width": 5,
      "height": 5,
      "angle": 45,
      "angleRad": 0.7853981633974483,
      "endzone": 0,
      "wall": 0,
      "hypotenuse": 3.5355339059327378,
      "corners": [
        [
          -3.5355339059327378,
          2.220446049250313e-16
        ],
        [
          2.220446049250313e-16,
          3.5355339059327378
        ],
        [
          3.5355339059327378,
          -2.220446049250313e-16
        ],
        [
          -2.220446049250313e-16,
          -3.5355339059327378
        ]
      ],
      "cornersSorted": [
        [
          -3.5355339059327378,
          2.220446049250313e-16
        ],
        [
          -2.220446049250313e-16,
          -3.5355339059327378
        ],
        [
          2.220446049250313e-16,
          3.5355339059327378
        ],
        [
          3.5355339059327378,
          -2.220446049250313e-16
        ]
      ],
      "leftMostCornerX": 536.4644660940672,
      "leftMostCornerY": 615,
      "rightMostCornerX": 543.5355339059328,
      "rightMostCornerY": 615,
      "topCornerX": 540,
      "topCornerY": 611.4644660940672,
      "botCornerX": 540,
      "botCornerY": 618.5355339059328,
      "occludes": [
        37
      ]
    },
    {
      "x": 555,
      "y": 615,
      "width": 5,
      "height": 5,
      "angle": 45,
      "angleRad": 0.7853981633974483,
      "endzone": 0,
      "wall": 0,
      "hypotenuse": 3.5355339059327378,
      "corners": [
        [
          -3.5355339059327378,
          2.220446049250313e-16
        ],
        [
          2.220446049250313e-16,
          3.5355339059327378
        ],
        [
          3.5355339059327378,
          -2.220446049250313e-16
        ],
        [
          -2.220446049250313e-16,
          -3.5355339059327378
        ]
      ],
      "cornersSorted": [
        [
          -3.5355339059327378,
          2.220446049250313e-16
        ],
        [
          -2.220446049250313e-16,
          -3.5355339059327378
        ],
        [
          2.220446049250313e-16,
          3.5355339059327378
        ],
        [
          3.5355339059327378,
          -2.220446049250313e-16
        ]
      ],
      "leftMostCornerX": 551.4644660940672,
      "leftMostCornerY": 615,
      "rightMostCornerX": 558.5355339059328,
      "rightMostCornerY": 615,
      "topCornerX": 555,
      "topCornerY": 611.4644660940672,
      "botCornerX": 555,
      "botCornerY": 618.5355339059328,
      "occludes": [
        36
      ]
    },
    {
      "x": 570,
      "y": 615,
      "width": 5,
      "height": 5,
      "angle": 45,
      "angleRad": 0.7853981633974483,
      "endzone": 0,
      "wall": 0,
      "hypotenuse": 3.5355339059327378,
      "corners": [
        [
          -3.5355339059327378,
          2.220446049250313e-16
        ],
        [
          2.220446049250313e-16,
          3.5355339059327378
        ],
        [
          3.5355339059327378,
          -2.220446049250313e-16
        ],
        [
          -2.220446049250313e-16,
          -3.5355339059327378
        ]
      ],
      "cornersSorted": [
        [
          -3.5355339059327378,
          2.220446049250313e-16
        ],
        [
          -2.220446049250313e-16,
          -3.5355339059327378
        ],
        [
          2.220446049250313e-16,
          3.5355339059327378
        ],
        [
          3.5355339059327378,
          -2.220446049250313e-16
        ]
      ],
      "leftMostCornerX": 566.4644660940672,
      "leftMostCornerY": 615,
      "rightMostCornerX": 573.5355339059328,
      "rightMostCornerY": 615,
      "topCornerX": 570,
      "topCornerY": 611.4644660940672,
      "botCornerX": 570,
      "botCornerY": 618.5355339059328,
      "occludes": [
        38
      ]
    },
    {
      "x": 585,
      "y": 615,
      "width": 5,
      "height": 5,
      "angle": 45,
      "angleRad": 0.7853981633974483,
      "endzone": 0,
      "wall": 0,
      "hypotenuse": 3.5355339059327378,
      "corners": [
        [
          -3.5355339059327378,
          2.220446049250313e-16
        ],
        [
          2.220446049250313e-16,
          3.5355339059327378
        ],
        [
          3.5355339059327378,
          -2.220446049250313e-16
        ],
        [
          -2.220446049250313e-16,
          -3.5355339059327378
        ]
      ],
      "cornersSorted": [
        [
          -3.5355339059327378,
          2.220446049250313e-16
        ],
        [
          -2.220446049250313e-16,
          -3.5355339059327378
        ],
        [
          2.220446049250313e-16,
          3.5355339059327378
        ],
        [
          3.5355339059327378,
          -2.220446049250313e-16
        ]
      ],
      "leftMostCornerX": 581.4644660940672,
      "leftMostCornerY": 615,
      "rightMostCornerX": 588.5355339059328,
      "rightMostCornerY": 615,
      "topCornerX": 585,
      "topCornerY": 611.4644660940672,
      "botCornerX": 585,
      "botCornerY": 618.5355339059328,
      "occludes": [
        39
      ]
    },
    {
      "x": 540,
      "y": 630,
      "width": 5,
      "height": 5,
      "angle": 45,
      "angleRad": 0.7853981633974483,
      "endzone": 0,
      "wall": 0,
      "hypotenuse": 3.5355339059327378,
      "corners": [
        [
          -3.5355339059327378,
          2.220446049250313e-16
        ],
        [
          2.220446049250313e-16,
          3.5355339059327378
        ],
        [
          3.5355339059327378,
          -2.220446049250313e-16
        ],
        [
          -2.220446049250313e-16,
          -3.5355339059327378
        ]
      ],
      "cornersSorted": [
        [
          -3.5355339059327378,
          2.220446049250313e-16
        ],
        [
          -2.220446049250313e-16,
          -3.5355339059327378
        ],
        [
          2.220446049250313e-16,
          3.5355339059327378
        ],
        [
          3.5355339059327378,
          -2.220446049250313e-16
        ]
      ],
      "leftMostCornerX": 536.4644660940672,
      "leftMostCornerY": 630,
      "rightMostCornerX": 543.5355339059328,
      "rightMostCornerY": 630,
      "topCornerX": 540,
      "topCornerY": 626.4644660940672,
      "botCornerX": 540,
      "botCornerY": 633.5355339059328,
      "occludes": [
        37,
        40
      ]
    },
    {
      "x": 555,
      "y": 630,
      "width": 5,
      "height": 5,
      "angle": 45,
      "angleRad": 0.7853981633974483,
      "endzone": 0,
      "wall": 0,
      "hypotenuse": 3.5355339059327378,
      "corners": [
        [
          -3.5355339059327378,
          2.220446049250313e-16
        ],
        [
          2.220446049250313e-16,
          3.5355339059327378
        ],
        [
          3.5355339059327378,
          -2.220446049250313e-16
        ],
        [
          -2.220446049250313e-16,
          -3.5355339059327378
        ]
      ],
      "cornersSorted": [
        [
          -3.5355339059327378,
          2.220446049250313e-16
        ],
        [
          -2.220446049250313e-16,
          -3.5355339059327378
        ],
        [
          2.220446049250313e-16,
          3.5355339059327378
        ],
        [
          3.5355339059327378,
          -2.220446049250313e-16
        ]
      ],
      "leftMostCornerX": 551.4644660940672,
      "leftMostCornerY": 630,
      "rightMostCornerX": 558.5355339059328,
      "rightMostCornerY": 630,
      "topCornerX": 555,
      "topCornerY": 626.4644660940672,
      "botCornerX": 555,
      "botCornerY": 633.5355339059328,
      "occludes": [
        36,
        41
      ]
    },
    {
      "x": 570,
      "y": 630,
      "width": 5,
      "height": 5,
      "angle": 45,
      "angleRad": 0.7853981633974483,
      "endzone": 0,
      "wall": 0,
      "hypotenuse": 3.5355339059327378,
      "corners": [
        [
          -3.5355339059327378,
          2.220446049250313e-16
        ],
        [
          2.220446049250313e-16,
          3.5355339059327378
        ],
        [
          3.5355339059327378,
          -2.220446049250313e-16
        ],
        [
          -2.220446049250313e-16,
          -3.5355339059327378
        ]
      ],
      "cornersSorted": [
        [
          -3.5355339059327378,
          2.220446049250313e-16
        ],
        [
          -2.220446049250313e-16,
          -3.5355339059327378
        ],
        [
          2.220446049250313e-16,
          3.5355339059327378
        ],
        [
          3.5355339059327378,
          -2.220446049250313e-16
        ]
      ],
      "leftMostCornerX": 566.4644660940672,
      "leftMostCornerY": 630,
      "rightMostCornerX": 573.5355339059328,
      "rightMostCornerY": 630,
      "topCornerX": 570,
      "topCornerY": 626.4644660940672,
      "botCornerX": 570,
      "botCornerY": 633.5355339059328,
      "occludes": [
        38,
        42
      ]
    },
    {
      "x": 585,
      "y": 630,
      "width": 5,
      "height": 5,
      "angle": 45,
      "angleRad": 0.7853981633974483,
      "endzone": 0,
      "wall": 0,
      "hypotenuse": 3.5355339059327378,
      "corners": [
        [
          -3.5355339059327378,
          2.220446049250313e-16
        ],
        [
          2.220446049250313e-16,
          3.5355339059327378
        ],
        [
          3.5355339059327378,
          -2.220446049250313e-16
        ],
        [
          -2.220446049250313e-16,
          -3.5355339059327378
        ]
      ],
      "cornersSorted": [
        [
          -3.5355339059327378,
          2.220446049250313e-16
        ],
        [
          -2.220446049250313e-16,
          -3.5355339059327378
        ],
        [
          2.220446049250313e-16,
          3.5355339059327378
        ],
        [
          3.5355339059327378,
          -2.220446049250313e-16
        ]
      ],
      "leftMostCornerX": 581.4644660940672,
      "leftMostCornerY": 630,
      "rightMostCornerX": 588.5355339059328,
      "rightMostCornerY": 630,
      "topCornerX": 585,
      "topCornerY": 626.4644660940672,
      "botCornerX": 585,
      "botCornerY": 633.5355339059328,
      "occludes": [
        39,
        43
      ]
    },
    {
      "x": 540,
      "y": 645,
      "width": 5,
      "height": 5,
      "angle": 45,
      "angleRad": 0.7853981633974483,
      "endzone": 0,
      "wall": 0,
      "hypotenuse": 3.5355339059327378,
      "corners": [
        [
          -3.5355339059327378,
          2.220446049250313e-16
        ],
        [
          2.220446049250313e-16,
          3.5355339059327378
        ],
        [
          3.5355339059327378,
          -2.220446049250313e-16
        ],
        [
          -2.220446049250313e-16,
          -3.5355339059327378
        ]
      ],
      "cornersSorted": [
        [
          -3.5355339059327378,
          2.220446049250313e-16
        ],
        [
          -2.220446049250313e-16,
          -3.5355339059327378
        ],
        [
          2.220446049250313e-16,
          3.5355339059327378
        ],
        [
          3.5355339059327378,
          -2.220446049250313e-16
        ]
      ],
      "leftMostCornerX": 536.4644660940672,
      "leftMostCornerY": 645,
      "rightMostCornerX": 543.5355339059328,
      "rightMostCornerY": 645,
      "topCornerX": 540,
      "topCornerY": 641.4644660940672,
      "botCornerX": 540,
      "botCornerY": 648.5355339059328,
      "occludes": [
        40,
        44
      ]
    },
    {
      "x": 555,
      "y": 645,
      "width": 5,
      "height": 5,
      "angle": 45,
      "angleRad": 0.7853981633974483,
      "endzone": 0,
      "wall": 0,
      "hypotenuse": 3.5355339059327378,
      "corners": [
        [
          -3.5355339059327378,
          2.220446049250313e-16
        ],
        [
          2.220446049250313e-16,
          3.5355339059327378
        ],
        [
          3.5355339059327378,
          -2.220446049250313e-16
        ],
        [
          -2.220446049250313e-16,
          -3.5355339059327378
        ]
      ],
      "cornersSorted": [
        [
          -3.5355339059327378,
          2.220446049250313e-16
        ],
        [
          -2.220446049250313e-16,
          -3.5355339059327378
        ],
        [
          2.220446049250313e-16,
          3.5355339059327378
        ],
        [
          3.5355339059327378,
          -2.220446049250313e-16
        ]
      ],
      "leftMostCornerX": 551.4644660940672,
      "leftMostCornerY": 645,
      "rightMostCornerX": 558.5355339059328,
      "rightMostCornerY": 645,
      "topCornerX": 555,
      "topCornerY": 641.4644660940672,
      "botCornerX": 555,
      "botCornerY": 648.5355339059328,
      "occludes": [
        41,
        45
      ]
    },
    {
      "x": 570,
      "y": 645,
      "width": 5,
      "height": 5,
      "angle": 45,
      "angleRad": 0.7853981633974483,
      "endzone": 0,
      "wall": 0,
      "hypotenuse": 3.5355339059327378,
      "corners": [
        [
          -3.5355339059327378,
          2.220446049250313e-16
        ],
        [
          2.220446049250313e-16,
          3.5355339059327378
        ],
        [
          3.5355339059327378,
          -2.220446049250313e-16
        ],
        [
          -2.220446049250313e-16,
          -3.5355339059327378
        ]
      ],
      "cornersSorted": [
        [
          -3.5355339059327378,
          2.220446049250313e-16
        ],
        [
          -2.220446049250313e-16,
          -3.5355339059327378
        ],
        [
          2.220446049250313e-16,
          3.5355339059327378
        ],
        [
          3.5355339059327378,
          -2.220446049250313e-16
        ]
      ],
      "leftMostCornerX": 566.4644660940672,
      "leftMostCornerY": 645,
      "rightMostCornerX": 573.5355339059328,
      "rightMostCornerY": 645,
      "topCornerX": 570,
      "topCornerY": 641.4644660940672,
      "botCornerX": 570,
      "botCornerY": 648.5355339059328,
      "occludes": [
        42,
        46
      ]
    },
    {
      "x": 585,
      "y": 645,
      "width": 5,
      "height": 5,
      "angle": 45,
      "angleRad": 0.7853981633974483,
      "endzone": 0,
      "wall": 0,
      "hypotenuse": 3.5355339059327378,
      "corners": [
        [
          -3.5355339059327378,
          2.220446049250313e-16
        ],
        [
          2.220446049250313e-16,
          3.5355339059327378
        ],
        [
          3.5355339059327378,
          -2.220446049250313e-16
        ],
        [
          -2.220446049250313e-16,
          -3.5355339059327378
        ]
      ],
      "cornersSorted": [
        [
          -3.5355339059327378,
          2.220446049250313e-16
        ],
        [
          -2.220446049250313e-16,
          -3.5355339059327378
        ],
        [
          2.220446049250313e-16,
          3.5355339059327378
        ],
        [
          3.5355339059327378,
          -2.220446049250313e-16
        ]
      ],
      "leftMostCornerX": 581.4644660940672,
      "leftMostCornerY": 645,
      "rightMostCornerX": 588.5355339059328,
      "rightMostCornerY": 645,
      "topCornerX": 585,
      "topCornerY": 641.4644660940672,
      "botCornerX": 585,
      "botCornerY": 648.5355339059328,
      "occludes": [
        43,
        47
      ]
    },
    {
      "x": 600,
      "y": 600,
      "width": 5,
      "height": 5,
      "angle": 45,
      "angleRad": 0.7853981633974483,
      "endzone": 0,
      "wall": 0,
      "hypotenuse": 3.5355339059327378,
      "corners": [
        [
          -3.5355339059327378,
          2.220446049250313e-16
        ],
        [
          2.220446049250313e-16,
          3.5355339059327378
        ],
        [
          3.5355339059327378,
          -2.220446049250313e-16
        ],
        [
          -2.220446049250313e-16,
          -3.5355339059327378
        ]
      ],
      "cornersSorted": [
        [
          -3.5355339059327378,
          2.220446049250313e-16
        ],
        [
          -2.220446049250313e-16,
          -3.5355339059327378
        ],
        [
          2.220446049250313e-16,
          3.5355339059327378
        ],
        [
          3.5355339059327378,
          -2.220446049250313e-16
        ]
      ],
      "leftMostCornerX": 596.4644660940672,
      "leftMostCornerY": 600,
      "rightMostCornerX": 603.5355339059328,
      "rightMostCornerY": 600,
      "topCornerX": 600,
      "topCornerY": 596.4644660940672,
      "botCornerX": 600,
      "botCornerY": 603.5355339059328,
      "occludes": []
    },
    {
      "x": 600,
      "y": 615,
      "width": 5,
      "height": 5,
      "angle": 45,
      "angleRad": 0.7853981633974483,
      "endzone": 0,
      "wall": 0,
      "hypotenuse": 3.5355339059327378,
      "corners": [
        [
          -3.5355339059327378,
          2.220446049250313e-16
        ],
        [
          2.220446049250313e-16,
          3.5355339059327378
        ],
        [
          3.5355339059327378,
          -2.220446049250313e-16
        ],
        [
          -2.220446049250313e-16,
          -3.5355339059327378
        ]
      ],
      "cornersSorted": [
        [
          -3.5355339059327378,
          2.220446049250313e-16
        ],
        [
          -2.220446049250313e-16,
          -3.5355339059327378
        ],
        [
          2.220446049250313e-16,
          3.5355339059327378
        ],
        [
          3.5355339059327378,
          -2.220446049250313e-16
        ]
      ],
      "leftMostCornerX": 596.4644660940672,
      "leftMostCornerY": 615,
      "rightMostCornerX": 603.5355339059328,
      "rightMostCornerY": 615,
      "topCornerX": 600,
      "topCornerY": 611.4644660940672,
      "botCornerX": 600,
      "botCornerY": 618.5355339059328,
      "occludes": [
        52
      ]
    },
    {
      "x": 600,
      "y": 630,
      "width": 5,
      "height": 5,
      "angle": 45,
      "angleRad": 0.7853981633974483,
      "endzone": 0,
      "wall": 0,
      "hypotenuse": 3.5355339059327378,
      "corners": [
        [
          -3.5355339059327378,
          2.220446049250313e-16
        ],
        [
          2.220446049250313e-16,
          3.5355339059327378
        ],
        [
          3.5355339059327378,
          -2.220446049250313e-16
        ],
        [
          -2.220446049250313e-16,
          -3.5355339059327378
        ]
      ],
      "cornersSorted": [
        [
          -3.5355339059327378,
          2.220446049250313e-16
        ],
        [
          -2.220446049250313e-16,
          -3.5355339059327378
        ],
        [
          2.220446049250313e-16,
          3.5355339059327378
        ],
        [
          3.5355339059327378,
          -2.220446049250313e-16
        ]
      ],
      "leftMostCornerX": 596.4644660940672,
      "leftMostCornerY": 630,
      "rightMostCornerX": 603.5355339059328,
      "rightMostCornerY": 630,
      "topCornerX": 600,
      "topCornerY": 626.4644660940672,
      "botCornerX": 600,
      "botCornerY": 633.5355339059328,
      "occludes": [
        52,
        53
      ]
    },
    {
      "x": 600,
      "y": 645,
      "width": 5,
      "height": 5,
      "angle": 45,
      "angleRad": 0.7853981633974483,
      "endzone": 0,
      "wall": 0,
      "hypotenuse": 3.5355339059327378,
      "corners": [
        [
          -3.5355339059327378,
          2.220446049250313e-16
        ],
        [
          2.220446049250313e-16,
          3.5355339059327378
        ],
        [
          3.5355339059327378,
          -2.220446049250313e-16
        ],
        [
          -2.220446049250313e-16,
          -3.5355339059327378
        ]
      ],
      "cornersSorted": [
        [
          -3.5355339059327378,
          2.220446049250313e-16
        ],
        [
          -2.220446049250313e-16,
          -3.5355339059327378
        ],
        [
          2.220446049250313e-16,
          3.5355339059327378
        ],
        [
          3.5355339059327378,
          -2.220446049250313e-16
        ]
      ],
      "leftMostCornerX": 596.4644660940672,
      "leftMostCornerY": 645,
      "rightMostCornerX": 603.5355339059328,
      "rightMostCornerY": 645,
      "topCornerX": 600,
      "topCornerY": 641.4644660940672,
      "botCornerX": 600,
      "botCornerY": 648.5355339059328,
      "occludes": [
        53,
        54
      ]
    }
  ]
}